{"is_source_file": true, "format": "Python", "description": "This is a Python source file that appears to serve as the initializer for an authentication package, likely defining or initializing authentication-related functionalities in a larger codebase.", "external_files": [], "external_methods": [], "published": [], "classes": [], "methods": [], "calls": [], "search-terms": ["auth", "authentication", "__init__.py", "package initialization"], "state": 2, "file_id": 9, "knowledge_revision": 18, "git_revision": "", "ctags": [], "hash": "0ff3ff2a15d6cb4a59770cf6ce141ef5", "format-version": 4, "code-base-name": "backend", "filename": "backend/src/auth/__init__.py", "revision_history": [{"18": ""}]}